hashtrack/__init__.py
hashtrack/__main__.py
hashtrack/config.yml
hashtrack/__pycache__/__init__.cpython-311.pyc
hashtrack/__pycache__/__main__.cpython-311.pyc
hashtrack/cmd/__init__.py
hashtrack/cmd/cache.py
hashtrack/cmd/check.py
hashtrack/cmd/config.py
hashtrack/cmd/init.py
hashtrack/cmd/update.py
hashtrack/cmd/watch.py
hashtrack/cmd/__pycache__/__init__.cpython-311.pyc
hashtrack/cmd/__pycache__/cache.cpython-311.pyc
hashtrack/cmd/__pycache__/check.cpython-311.pyc
hashtrack/cmd/__pycache__/config.cpython-311.pyc
hashtrack/cmd/__pycache__/init.cpython-311.pyc
hashtrack/cmd/__pycache__/update.cpython-311.pyc
hashtrack/cmd/__pycache__/watch.cpython-311.pyc
hashtrack/utils/__init__.py
hashtrack/utils/constants.py
hashtrack/utils/log.py
hashtrack/utils/misc.py
hashtrack/utils/__pycache__/__init__.cpython-311.pyc
hashtrack/utils/__pycache__/constants.cpython-311.pyc
hashtrack/utils/__pycache__/log.cpython-311.pyc
hashtrack/utils/__pycache__/misc.cpython-311.pyc
hashtrack-0.0.1.dist-info/LICENSE
hashtrack-0.0.1.dist-info/METADATA
hashtrack-0.0.1.dist-info/WHEEL
hashtrack-0.0.1.dist-info/entry_points.txt
hashtrack-0.0.1.dist-info/top_level.txt
hashtrack-0.0.1.dist-info/RECORD
