Metadata-Version: 2.1
Name: hashtrack
Version: 0.0.1
Summary: A cli tool to track file changes via checksums
Project-URL: Github, https://github.com/fkcptlst/hashtrack
Classifier: Programming Language :: Python :: 3
Classifier: License :: OSI Approved :: Apache Software License
Requires-Python: >=3.8
License-File: LICENSE
Requires-Dist: click
Requires-Dist: pyyaml
Requires-Dist: addict
Requires-Dist: loguru
Provides-Extra: dev
Requires-Dist: pytest ~=7.4.3 ; extra == 'dev'
Requires-Dist: pytest-cov ~=4.1.0 ; extra == 'dev'
Requires-Dist: build ; extra == 'dev'
Requires-Dist: twine ; extra == 'dev'
